analytics/__init__.py
analytics/errors.py
analytics/main.py
analytics/test.py
atados_analytics_sdk-0.0.4b1.dist-info/METADATA
atados_analytics_sdk-0.0.4b1.dist-info/WHEEL
atados_analytics_sdk-0.0.4b1.dist-info/top_level.txt
atados_analytics_sdk-0.0.4b1.dist-info/RECORD
