Metadata-Version: 2.1
Name: atados-analytics-sdk
Version: 0.0.4b1
Summary: Analytics SDK
Home-page: https://github.com/atados/analytics/tree/master/sdk/python
Author: Vinicius Pacheco Furtado
Author-email: pacheco@atados.com.br
License: UNKNOWN
Platform: UNKNOWN
Classifier: Programming Language :: Python :: 3
Classifier: License :: OSI Approved :: MIT License
Classifier: Operating System :: OS Independent
Requires-Python: >=3.6
Requires-Dist: requests
